CHANGES.txt
LICENSE.txt
README.txt
bootstrap.py
buildout.cfg
setup.py
src/zope/__init__.py
src/zope.httpform.egg-info/PKG-INFO
src/zope.httpform.egg-info/SOURCES.txt
src/zope.httpform.egg-info/dependency_links.txt
src/zope.httpform.egg-info/namespace_packages.txt
src/zope.httpform.egg-info/not-zip-safe
src/zope.httpform.egg-info/requires.txt
src/zope.httpform.egg-info/top_level.txt
src/zope/httpform/README.txt
src/zope/httpform/__init__.py
src/zope/httpform/interfaces.py
src/zope/httpform/parser.py
src/zope/httpform/tests.py
src/zope/httpform/typeconv.py