Metadata-Version: 1.0
Name: zope.httpform
Version: 1.0.1
Summary: HTTP Form Data Parser
Home-page: http://pypi.python.org/pypi/zope.httpform
Author: Zope Corporation and Contributors
Author-email: zope-dev@zope.org
License: ZPL 2.1
Platform: UNKNOWN
Classifier: Development Status :: 4 - Beta
Classifier: Intended Audience :: Developers
Classifier: Programming Language :: Python
Classifier: Environment :: Web Environment
Classifier: Topic :: Internet :: WWW/HTTP :: WSGI :: Application
Classifier: Framework :: Zope3
